mongogbackup/__init__.py
mongogbackup/backups.py
mongogbackup/files.py
mongogbackup/gdrive.py
mongogbackup/targz.py
mongogbackup-0.1.1.dist-info/METADATA
mongogbackup-0.1.1.dist-info/WHEEL
mongogbackup-0.1.1.dist-info/licenses/LICENSE
mongogbackup-0.1.1.dist-info/RECORD
