Metadata-Version: 2.3
Name: mongogbackup
Version: 0.1.1
Summary: Securely Backup MongoDB to Google Drive
Project-URL: Repository, https://github.com/DevCom-IITB/mongogbackup
Project-URL: Issues, https://github.com/DevCom-IITB/mongogbackup/issues
Author-email: "DevCom, IIT Bombay" <devcom@iitb.ac.in>
Maintainer-email: "DevCom, IIT Bombay" <devcom@iitb.ac.in>
License: MIT License
License-File: LICENSE
Keywords: backup,drive,gdrive,google,mongo,mongodb,mongogb,mongogbackup,remote
Classifier: Development Status :: 5 - Production/Stable
Classifier: Intended Audience :: Developers
Classifier: License :: OSI Approved :: MIT License
Classifier: Programming Language :: Python
Requires-Python: >=3.8
Requires-Dist: cryptography>=42.0.8
Requires-Dist: google-api-python-client>=2.136.0
Requires-Dist: google-auth-httplib2>=0.2.0
Requires-Dist: google-auth-oauthlib>=1.2.0
Requires-Dist: google-auth>=2.31.0
Requires-Dist: pymongo>=4.8.0
Requires-Dist: requests>=2.31.0
